RForDataScience/README.md
RForDataScience/__init__.py
RForDataScience/__main__.py
RForDataScience/file.epub
RForDataScience/index.html
RForDataScience/css/__init__.py
RForDataScience/css/annotations.css
RForDataScience/css/main.css
RForDataScience/css/normalize.css
RForDataScience/css/popup.css
RForDataScience/font/__init__.py
RForDataScience/font/fontello.eot
RForDataScience/font/fontello.svg
RForDataScience/font/fontello.ttf
RForDataScience/font/fontello.woff
RForDataScience/img/__init__.py
RForDataScience/img/annotator-glyph-sprite.png
RForDataScience/img/annotator-icon-sprite.png
RForDataScience/img/apple-touch-icon.png
RForDataScience/img/cancelfullscreen.png
RForDataScience/img/close.png
RForDataScience/img/fullscreen.png
RForDataScience/img/loader.gif
RForDataScience/img/menu-icon.png
RForDataScience/img/save.png
RForDataScience/img/saved.png
RForDataScience/img/settings-s.png
RForDataScience/img/settings.png
RForDataScience/img/star.png
RForDataScience/js/__init__.py
RForDataScience/js/epub.js
RForDataScience/js/epub.min.js
RForDataScience/js/epub.min.map
RForDataScience/js/hooks.min.js
RForDataScience/js/hooks.min.map
RForDataScience/js/reader.js
RForDataScience/js/reader.js.map
RForDataScience/js/reader.min.js
RForDataScience/js/reader.min.map
RForDataScience/js/hooks/__init__.py
RForDataScience/js/hooks/extensions/__init__.py
RForDataScience/js/hooks/extensions/highlight.js
RForDataScience/js/libs/__init__.py
RForDataScience/js/libs/jquery.min.js
RForDataScience/js/libs/localforage.min.js
RForDataScience/js/libs/screenfull.js
RForDataScience/js/libs/screenfull.min.js
RForDataScience/js/libs/zip.min.js
RForDataScience/js/plugins/__init__.py
RForDataScience/js/plugins/hypothesis.js
RForDataScience/js/plugins/search.js
r_for_data_science-2024.3.4.0.dist-info/METADATA
r_for_data_science-2024.3.4.0.dist-info/WHEEL
r_for_data_science-2024.3.4.0.dist-info/entry_points.txt
r_for_data_science-2024.3.4.0.dist-info/top_level.txt
r_for_data_science-2024.3.4.0.dist-info/RECORD
